{"box_data": [{"position": {"minX": 48.0, "minY": 197.25, "maxX": 320.25, "maxY": 285.25}, "class_id": 0, "box_caption": "Wooden-Pallet 0.810", "scores": {"class_score": 0.8095703125}, "domain": "pixel"}, {"position": {"minX": 53.5, "minY": 268.0, "maxX": 324.75, "maxY": 326.5}, "class_id": 0, "box_caption": "Wooden-Pallet 0.012", "scores": {"class_score": 0.0116424560546875}, "domain": "pixel"}, {"position": {"minX": 49.0, "minY": 202.25, "maxX": 244.0, "maxY": 275.25}, "class_id": 0, "box_caption": "Wooden-Pallet 0.007", "scores": {"class_score": 0.007232666015625}, "domain": "pixel"}, {"position": {"minX": 60.5625, "minY": 154.0, "maxX": 308.25, "maxY": 227.5}, "class_id": 0, "box_caption": "Wooden-Pallet 0.005", "scores": {"class_score": 0.004791259765625}, "domain": "pixel"}, {"position": {"minX": 25.34375, "minY": -3.4375, "maxX": 55.59375, "maxY": 30.1875}, "class_id": 0, "box_caption": "Wooden-Pallet 0.005", "scores": {"class_score": 0.004756927490234375}, "domain": "pixel"}, {"position": {"minX": 16.1875, "minY": -3.5703125, "maxX": 45.65625, "maxY": 30.65625}, "class_id": 0, "box_caption": "Wooden-Pallet 0.004", "scores": {"class_score": 0.00399017333984375}, "domain": "pixel"}, {"position": {"minX": 160.25, "minY": 29.4375, "maxX": 361.75, "maxY": 205.75}, "class_id": 0, "box_caption": "Wooden-Pallet 0.004", "scores": {"class_score": 0.003765106201171875}, "domain": "pixel"}, {"position": {"minX": 188.0, "minY": 212.5, "maxX": 325.0, "maxY": 283.5}, "class_id": 0, "box_caption": "Wooden-Pallet 0.004", "scores": {"class_score": 0.0036640167236328125}, "domain": "pixel"}, {"position": {"minX": 54.875, "minY": 249.25, "maxX": 331.5, "maxY": 353.75}, "class_id": 0, "box_caption": "Wooden-Pallet 0.003", "scores": {"class_score": 0.0033245086669921875}, "domain": "pixel"}, {"position": {"minX": 37.625, "minY": 122.625, "maxX": 320.5, "maxY": 244.125}, "class_id": 0, "box_caption": "Wooden-Pallet 0.003", "scores": {"class_score": 0.00269317626953125}, "domain": "pixel"}, {"position": {"minX": 262.75, "minY": 202.75, "maxX": 335.25, "maxY": 225.0}, "class_id": 0, "box_caption": "Wooden-Pallet 0.003", "scores": {"class_score": 0.0025310516357421875}, "domain": "pixel"}, {"position": {"minX": 195.625, "minY": 251.125, "maxX": 325.5, "maxY": 284.75}, "class_id": 0, "box_caption": "Wooden-Pallet 0.002", "scores": {"class_score": 0.002269744873046875}, "domain": "pixel"}, {"position": {"minX": 196.75, "minY": 7.3125, "maxX": 382.75, "maxY": 178.0}, "class_id": 0, "box_caption": "Wooden-Pallet 0.002", "scores": {"class_score": 0.0022602081298828125}, "domain": "pixel"}, {"position": {"minX": 226.0, "minY": 260.75, "maxX": 333.0, "maxY": 287.25}, "class_id": 0, "box_caption": "Wooden-Pallet 0.002", "scores": {"class_score": 0.0019044876098632812}, "domain": "pixel"}, {"position": {"minX": 206.375, "minY": 31.1875, "maxX": 342.5, "maxY": 129.0}, "class_id": 0, "box_caption": "Wooden-Pallet 0.002", "scores": {"class_score": 0.0017480850219726562}, "domain": "pixel"}, {"position": {"minX": 6.78125, "minY": -12.46875, "maxX": 70.0, "maxY": 37.53125}, "class_id": 0, "box_caption": "Wooden-Pallet 0.002", "scores": {"class_score": 0.001720428466796875}, "domain": "pixel"}, {"position": {"minX": 40.28125, "minY": 188.25, "maxX": 143.875, "maxY": 229.0}, "class_id": 0, "box_caption": "Wooden-Pallet 0.002", "scores": {"class_score": 0.0017070770263671875}, "domain": "pixel"}, {"position": {"minX": 288.0, "minY": 131.5, "maxX": 309.5, "maxY": 161.25}, "class_id": 0, "box_caption": "Wooden-Pallet 0.002", "scores": {"class_score": 0.0016679763793945312}, "domain": "pixel"}, {"position": {"minX": 29.46875, "minY": 227.75, "maxX": 98.75, "maxY": 273.0}, "class_id": 0, "box_caption": "Wooden-Pallet 0.002", "scores": {"class_score": 0.0016489028930664062}, "domain": "pixel"}, {"position": {"minX": 31.5, "minY": -14.125, "maxX": 287.5, "maxY": 264.5}, "class_id": 0, "box_caption": "Wooden-Pallet 0.002", "scores": {"class_score": 0.0016422271728515625}, "domain": "pixel"}, {"position": {"minX": 245.5, "minY": -0.21875, "maxX": 364.5, "maxY": 79.5}, "class_id": 0, "box_caption": "Wooden-Pallet 0.002", "scores": {"class_score": 0.0016422271728515625}, "domain": "pixel"}, {"position": {"minX": 55.53125, "minY": 208.125, "maxX": 182.0, "maxY": 269.75}, "class_id": 0, "box_caption": "Wooden-Pallet 0.002", "scores": {"class_score": 0.00157928466796875}, "domain": "pixel"}, {"position": {"minX": 280.0, "minY": -17.046875, "maxX": 372.0, "maxY": 19.484375}, "class_id": 0, "box_caption": "Wooden-Pallet 0.001", "scores": {"class_score": 0.001495361328125}, "domain": "pixel"}, {"position": {"minX": 36.875, "minY": 154.5, "maxX": 190.125, "maxY": 216.0}, "class_id": 0, "box_caption": "Wooden-Pallet 0.001", "scores": {"class_score": 0.0014896392822265625}, "domain": "pixel"}, {"position": {"minX": 166.0, "minY": 54.96875, "maxX": 328.5, "maxY": 179.75}, "class_id": 0, "box_caption": "Wooden-Pallet 0.001", "scores": {"class_score": 0.001483917236328125}, "domain": "pixel"}, {"position": {"minX": 195.125, "minY": 200.875, "maxX": 328.0, "maxY": 229.125}, "class_id": 0, "box_caption": "Wooden-Pallet 0.001", "scores": {"class_score": 0.0014781951904296875}, "domain": "pixel"}, {"position": {"minX": 256.0, "minY": 1.5, "maxX": 352.5, "maxY": 31.84375}, "class_id": 0, "box_caption": "Wooden-Pallet 0.001", "scores": {"class_score": 0.0014495849609375}, "domain": "pixel"}, {"position": {"minX": 196.5, "minY": 195.25, "maxX": 329.0, "maxY": 221.25}, "class_id": 0, "box_caption": "Wooden-Pallet 0.001", "scores": {"class_score": 0.0014047622680664062}, "domain": "pixel"}, {"position": {"minX": 49.03125, "minY": 255.125, "maxX": 103.0, "maxY": 272.25}, "class_id": 0, "box_caption": "Wooden-Pallet 0.001", "scores": {"class_score": 0.0013885498046875}, "domain": "pixel"}, {"position": {"minX": 103.6875, "minY": 85.75, "maxX": 252.75, "maxY": 163.75}, "class_id": 0, "box_caption": "Wooden-Pallet 0.001", "scores": {"class_score": 0.0013723373413085938}, "domain": "pixel"}, {"position": {"minX": 177.125, "minY": -94.75, "maxX": 401.5, "maxY": 189.5}, "class_id": 0, "box_caption": "Wooden-Pallet 0.001", "scores": {"class_score": 0.0013456344604492188}, "domain": "pixel"}, {"position": {"minX": 47.53125, "minY": 216.5, "maxX": 143.25, "maxY": 269.75}, "class_id": 0, "box_caption": "Wooden-Pallet 0.001", "scores": {"class_score": 0.00128936767578125}, "domain": "pixel"}, {"position": {"minX": 252.25, "minY": 260.5, "maxX": 328.75, "maxY": 281.0}, "class_id": 0, "box_caption": "Wooden-Pallet 0.001", "scores": {"class_score": 0.0012788772583007812}, "domain": "pixel"}, {"position": {"minX": 277.5, "minY": 144.5, "maxX": 318.0, "maxY": 167.5}, "class_id": 0, "box_caption": "Wooden-Pallet 0.001", "scores": {"class_score": 0.001201629638671875}, "domain": "pixel"}, {"position": {"minX": 35.25, "minY": 285.25, "maxX": 327.75, "maxY": 344.75}, "class_id": 0, "box_caption": "Wooden-Pallet 0.001", "scores": {"class_score": 0.001178741455078125}, "domain": "pixel"}, {"position": {"minX": 253.75, "minY": -8.078125, "maxX": 339.25, "maxY": 25.015625}, "class_id": 0, "box_caption": "Wooden-Pallet 0.001", "scores": {"class_score": 0.0010986328125}, "domain": "pixel"}, {"position": {"minX": 43.75, "minY": 195.5, "maxX": 154.0, "maxY": 216.25}, "class_id": 0, "box_caption": "Wooden-Pallet 0.001", "scores": {"class_score": 0.0010900497436523438}, "domain": "pixel"}, {"position": {"minX": 66.625, "minY": 59.1875, "maxX": 333.5, "maxY": 192.25}, "class_id": 0, "box_caption": "Wooden-Pallet 0.001", "scores": {"class_score": 0.0010404586791992188}, "domain": "pixel"}, {"position": {"minX": 25.03125, "minY": 249.5, "maxX": 98.625, "maxY": 288.0}, "class_id": 0, "box_caption": "Wooden-Pallet 0.001", "scores": {"class_score": 0.0010242462158203125}, "domain": "pixel"}, {"position": {"minX": 135.25, "minY": 185.75, "maxX": 336.25, "maxY": 302.0}, "class_id": 0, "box_caption": "Wooden-Pallet 0.001", "scores": {"class_score": 0.0010166168212890625}, "domain": "pixel"}, {"position": {"minX": 97.5625, "minY": 203.25, "maxX": 322.75, "maxY": 238.25}, "class_id": 0, "box_caption": "Wooden-Pallet 0.001", "scores": {"class_score": 0.0010118484497070312}, "domain": "pixel"}], "class_labels": {"0": "Wooden-Pallet"}}