{"box_data": [{"position": {"minX": 78.73515319824219, "minY": 132.40206909179688, "maxX": 526.0990600585938, "maxY": 377.8755798339844}, "class_id": 0, "box_caption": "Wooden-Pallet 0.839", "scores": {"class_score": 0.8389495611190796}, "domain": "pixel"}, {"position": {"minX": 12.248443603515625, "minY": 412.99127197265625, "maxX": 44.47736358642578, "maxY": 505.18017578125}, "class_id": 0, "box_caption": "Wooden-Pallet 0.002", "scores": {"class_score": 0.0022601627279073}, "domain": "pixel"}, {"position": {"minX": 4.909618377685547, "minY": 382.6145324707031, "maxX": 42.65474319458008, "maxY": 512.215576171875}, "class_id": 0, "box_caption": "Wooden-Pallet 0.002", "scores": {"class_score": 0.0016724530141800642}, "domain": "pixel"}, {"position": {"minX": 311.6510925292969, "minY": 144.66763305664062, "maxX": 516.5820922851562, "maxY": 381.8126525878906}, "class_id": 0, "box_caption": "Wooden-Pallet 0.001", "scores": {"class_score": 0.0013945370446890593}, "domain": "pixel"}, {"position": {"minX": 433.7764892578125, "minY": 197.72052001953125, "maxX": 522.4758911132812, "maxY": 338.33990478515625}, "class_id": 0, "box_caption": "Wooden-Pallet 0.001", "scores": {"class_score": 0.001178749487735331}, "domain": "pixel"}], "class_labels": {"0": "Wooden-Pallet"}}