{"box_data": [{"position": {"minX": 93.80526733398438, "minY": 194.03872680664062, "maxX": 635.121337890625, "maxY": 293.4842834472656}, "class_id": 0, "box_caption": "Wooden-Pallet 0.773", "scores": {"class_score": 0.7726241946220398}, "domain": "pixel"}, {"position": {"minX": 98.99856567382812, "minY": 446.3646545410156, "maxX": 635.442138671875, "maxY": 542.4533081054688}, "class_id": 0, "box_caption": "Wooden-Pallet 0.640", "scores": {"class_score": 0.6403999328613281}, "domain": "pixel"}, {"position": {"minX": 92.04092407226562, "minY": 364.69976806640625, "maxX": 631.380615234375, "maxY": 453.73480224609375}, "class_id": 0, "box_caption": "Wooden-Pallet 0.506", "scores": {"class_score": 0.5061095356941223}, "domain": "pixel"}, {"position": {"minX": 72.54812622070312, "minY": 78.1490249633789, "maxX": 661.633544921875, "maxY": 221.81668090820312}, "class_id": 0, "box_caption": "Wooden-Pallet 0.462", "scores": {"class_score": 0.46177566051483154}, "domain": "pixel"}, {"position": {"minX": 91.91458129882812, "minY": 282.9015197753906, "maxX": 626.0269775390625, "maxY": 389.8070373535156}, "class_id": 0, "box_caption": "Wooden-Pallet 0.428", "scores": {"class_score": 0.42827358841896057}, "domain": "pixel"}, {"position": {"minX": 168.58816528320312, "minY": 92.10447692871094, "maxX": 598.76171875, "maxY": 209.58265686035156}, "class_id": 0, "box_caption": "Wooden-Pallet 0.006", "scores": {"class_score": 0.0061978972516953945}, "domain": "pixel"}, {"position": {"minX": 42.24028015136719, "minY": 85.21630859375, "maxX": 269.4775390625, "maxY": 202.21804809570312}, "class_id": 0, "box_caption": "Wooden-Pallet 0.003", "scores": {"class_score": 0.003343810560181737}, "domain": "pixel"}, {"position": {"minX": 55.77032470703125, "minY": 452.0794677734375, "maxX": 290.97357177734375, "maxY": 554.3111572265625}, "class_id": 0, "box_caption": "Wooden-Pallet 0.003", "scores": {"class_score": 0.0031147815752774477}, "domain": "pixel"}, {"position": {"minX": 624.7469482421875, "minY": 242.22576904296875, "maxX": 663.8541259765625, "maxY": 408.88543701171875}, "class_id": 0, "box_caption": "Wooden-Pallet 0.001", "scores": {"class_score": 0.0012467260239645839}, "domain": "pixel"}, {"position": {"minX": 15.7503662109375, "minY": 191.24916076660156, "maxX": 496.0009460449219, "maxY": 284.8527526855469}, "class_id": 0, "box_caption": "Wooden-Pallet 0.001", "scores": {"class_score": 0.0012142874766141176}, "domain": "pixel"}], "class_labels": {"0": "Wooden-Pallet"}}