{"box_data": [{"position": {"minX": 66.5, "minY": 134.25, "maxX": 313.75, "maxY": 236.25}, "class_id": 0, "box_caption": "Wooden-Pallet 0.927", "scores": {"class_score": 0.92724609375}, "domain": "pixel"}, {"position": {"minX": 53.875, "minY": 81.4375, "maxX": 311.5, "maxY": 183.75}, "class_id": 0, "box_caption": "Wooden-Pallet 0.886", "scores": {"class_score": 0.88623046875}, "domain": "pixel"}, {"position": {"minX": 68.5, "minY": 199.25, "maxX": 317.25, "maxY": 291.25}, "class_id": 0, "box_caption": "Wooden-Pallet 0.824", "scores": {"class_score": 0.82421875}, "domain": "pixel"}, {"position": {"minX": 73.5, "minY": 82.375, "maxX": 305.75, "maxY": 148.0}, "class_id": 0, "box_caption": "Wooden-Pallet 0.018", "scores": {"class_score": 0.0177764892578125}, "domain": "pixel"}, {"position": {"minX": 335.5, "minY": 176.5, "maxX": 351.0, "maxY": 319.5}, "class_id": 0, "box_caption": "Wooden-Pallet 0.004", "scores": {"class_score": 0.00394439697265625}, "domain": "pixel"}, {"position": {"minX": 81.0, "minY": 119.5625, "maxX": 309.25, "maxY": 181.0}, "class_id": 0, "box_caption": "Wooden-Pallet 0.003", "scores": {"class_score": 0.0026531219482421875}, "domain": "pixel"}, {"position": {"minX": 70.625, "minY": 171.5, "maxX": 306.0, "maxY": 245.5}, "class_id": 0, "box_caption": "Wooden-Pallet 0.003", "scores": {"class_score": 0.002590179443359375}, "domain": "pixel"}, {"position": {"minX": 338.25, "minY": 144.0, "maxX": 351.25, "maxY": 294.25}, "class_id": 0, "box_caption": "Wooden-Pallet 0.002", "scores": {"class_score": 0.0021152496337890625}, "domain": "pixel"}, {"position": {"minX": 339.0, "minY": 128.25, "maxX": 351.5, "maxY": 215.5}, "class_id": 0, "box_caption": "Wooden-Pallet 0.002", "scores": {"class_score": 0.0015010833740234375}, "domain": "pixel"}, {"position": {"minX": 330.25, "minY": 212.25, "maxX": 350.25, "maxY": 312.75}, "class_id": 0, "box_caption": "Wooden-Pallet 0.001", "scores": {"class_score": 0.0014667510986328125}, "domain": "pixel"}, {"position": {"minX": 336.5, "minY": 219.5, "maxX": 350.5, "maxY": 334.5}, "class_id": 0, "box_caption": "Wooden-Pallet 0.001", "scores": {"class_score": 0.0012063980102539062}, "domain": "pixel"}, {"position": {"minX": 330.5, "minY": 168.5, "maxX": 351.5, "maxY": 268.5}, "class_id": 0, "box_caption": "Wooden-Pallet 0.001", "scores": {"class_score": 0.0011653900146484375}, "domain": "pixel"}], "class_labels": {"0": "Wooden-Pallet"}}